<?xml version="1.0" encoding="utf-8"?>
<ArrayOfCustomerDal xmlns:xsi="http://www.w3.org/2001/XMLSchema-instance" xmlns:xsd="http://www.w3.org/2001/XMLSchema">
  <CustomerDal>
    <Id>877600717</Id>
    <Name>Aviad</Name>
    <Phone>0546792435</Phone>
    <Longitude>31.90562629699707</Longitude>
    <Latitude>34.899192810058594</Latitude>
  </CustomerDal>
  <CustomerDal>
    <Id>991518257</Id>
    <Name>Avi</Name>
    <Phone>0571535632</Phone>
    <Longitude>32.19121551513672</Longitude>
    <Latitude>34.82804489135742</Latitude>
  </CustomerDal>
  <CustomerDal>
    <Id>864455329</Id>
    <Name>Evyatar</Name>
    <Phone>0586034500</Phone>
    <Longitude>32.07841873168945</Longitude>
    <Latitude>34.862518310546875</Latitude>
  </CustomerDal>
  <CustomerDal>
    <Id>720385507</Id>
    <Name>Dan</Name>
    <Phone>0536762550</Phone>
    <Longitude>32.113380432128906</Longitude>
    <Latitude>34.64077377319336</Latitude>
  </CustomerDal>
  <CustomerDal>
    <Id>195518392</Id>
    <Name>Gad</Name>
    <Phone>0542725176</Phone>
    <Longitude>31.94610595703125</Longitude>
    <Latitude>34.87763214111328</Latitude>
  </CustomerDal>
  <CustomerDal>
    <Id>812963486</Id>
    <Name>Gal</Name>
    <Phone>0545484670</Phone>
    <Longitude>32.12601089477539</Longitude>
    <Latitude>34.871978759765625</Latitude>
  </CustomerDal>
  <CustomerDal>
    <Id>337856136</Id>
    <Name>John</Name>
    <Phone>0547753566</Phone>
    <Longitude>31.991294860839844</Longitude>
    <Latitude>34.759559631347656</Latitude>
  </CustomerDal>
  <CustomerDal>
    <Id>818320902</Id>
    <Name>Mike</Name>
    <Phone>0573825874</Phone>
    <Longitude>32.124576568603516</Longitude>
    <Latitude>34.7785530090332</Latitude>
  </CustomerDal>
  <CustomerDal>
    <Id>492001250</Id>
    <Name>Eli</Name>
    <Phone>0545715302</Phone>
    <Longitude>32.07079315185547</Longitude>
    <Latitude>34.88648223876953</Latitude>
  </CustomerDal>
  <CustomerDal>
    <Id>932021348</Id>
    <Name>Michael</Name>
    <Phone>0574436143</Phone>
    <Longitude>31.81865882873535</Longitude>
    <Latitude>34.95890808105469</Latitude>
  </CustomerDal>
  <CustomerDal>
    <Id>314960881</Id>
    <Name>Aviad</Name>
    <Phone>0549107107</Phone>
    <Longitude>32.4</Longitude>
    <Latitude>34.6</Latitude>
  </CustomerDal>
  <CustomerDal>
    <Id>208500553</Id>
    <Name>Efrat</Name>
    <Phone>0587133002</Phone>
    <Longitude>32.5</Longitude>
    <Latitude>34.55</Latitude>
  </CustomerDal>
  <CustomerDal>
    <Id>315487564</Id>
    <Name>Eyal</Name>
    <Phone>0549107105</Phone>
    <Longitude>32.4</Longitude>
    <Latitude>36.4</Latitude>
  </CustomerDal>
</ArrayOfCustomerDal>